LICENSE.txt
setup.cfg
setup.py
finalGZ/Package.py
finalGZ/__init__.py
finalGZ.egg-info/PKG-INFO
finalGZ.egg-info/SOURCES.txt
finalGZ.egg-info/dependency_links.txt
finalGZ.egg-info/requires.txt
finalGZ.egg-info/top_level.txt
finalGZ/DATA/100008.jpg
finalGZ/DATA/100023.jpg
finalGZ/DATA/100053.jpg
finalGZ/DATA/100078.jpg
finalGZ/DATA/100090.jpg
finalGZ/DATA/100122.jpg
finalGZ/DATA/100123.jpg
finalGZ/DATA/100128.jpg
finalGZ/DATA/100134.jpg
finalGZ/DATA/100143.jpg
finalGZ/DATA/100150.jpg
finalGZ/DATA/100157.jpg
finalGZ/DATA/100204.jpg
finalGZ/DATA/100237.jpg
finalGZ/DATA/100259.jpg
finalGZ/DATA/100263.jpg
finalGZ/DATA/100288.jpg
finalGZ/DATA/100295.jpg
finalGZ/DATA/100322.jpg
finalGZ/DATA/100335.jpg
finalGZ/DATA/100380.jpg
finalGZ/DATA/100382.jpg
finalGZ/DATA/100383.jpg
finalGZ/DATA/100402.jpg
finalGZ/DATA/100428.jpg
finalGZ/DATA/100434.jpg
finalGZ/DATA/100444.jpg
finalGZ/DATA/100445.jpg
finalGZ/DATA/100458.jpg
finalGZ/DATA/100474.jpg
finalGZ/DATA/100479.jpg
finalGZ/DATA/100506.jpg
finalGZ/DATA/100513.jpg
finalGZ/DATA/100520.jpg
finalGZ/DATA/100541.jpg
finalGZ/DATA/100561.jpg
finalGZ/DATA/100571.jpg
finalGZ/DATA/100601.jpg
finalGZ/DATA/100623.jpg
finalGZ/DATA/100672.jpg
finalGZ/DATA/100673.jpg
finalGZ/DATA/100724.jpg
finalGZ/DATA/100727.jpg
finalGZ/DATA/100730.jpg
finalGZ/DATA/100740.jpg
finalGZ/DATA/100744.jpg
finalGZ/DATA/100765.jpg
finalGZ/DATA/100774.jpg
finalGZ/DATA/100801.jpg
finalGZ/DATA/100813.jpg
finalGZ/DATA/100821.jpg
finalGZ/DATA/100822.jpg
finalGZ/DATA/100836.jpg
finalGZ/DATA/100852.jpg
finalGZ/DATA/100859.jpg
finalGZ/DATA/100861.jpg
finalGZ/DATA/100867.jpg
finalGZ/DATA/100887.jpg
finalGZ/DATA/100894.jpg
finalGZ/DATA/100938.jpg
finalGZ/DATA/100951.jpg
finalGZ/DATA/100986.jpg
finalGZ/DATA/101007.jpg
finalGZ/DATA/101061.jpg
finalGZ/DATA/101074.jpg
finalGZ/DATA/101092.jpg
finalGZ/DATA/101127.jpg
finalGZ/DATA/101133.jpg
finalGZ/DATA/101135.jpg
finalGZ/DATA/101140.jpg
finalGZ/DATA/101151.jpg
finalGZ/DATA/101164.jpg
finalGZ/DATA/101166.jpg
finalGZ/DATA/101181.jpg
finalGZ/DATA/101232.jpg
finalGZ/DATA/101239.jpg
finalGZ/DATA/101244.jpg
finalGZ/DATA/101246.jpg
finalGZ/DATA/101247.jpg
finalGZ/DATA/101251.jpg
